{
  "prontuario_id": 107,
  "text": "PO de exérese de lipoma em região de crista ilíaca esquerda.\nFO bem cicatrizada.\nAP: CISTOADENOMA APÓCRINO. \nMARGENS CIRÚRGICAS LIVRES.\n\nAlta por cirurgia geral.\n",
  "entities": {
    "Conceito Temporal": [
      "PO"
    ],
    "Abreviação": [
      "PO",
      "AP",
      "FO bem cicatrizada"
    ],
    "Atividade de Assistência à Saúde": [
      "Alta"
    ],
    "Procedimento Terapêutico ou Preventivo": [
      "exérese de lipoma"
    ],
    "Localização ou Região Corporal": [
      "crista ilíaca esquerda"
    ],
    "Achado": [
      "FO bem cicatrizada",
      "MARGENS CIRÚRGICAS LIVRES"
    ],
    "Processo Neoplásico": [
      "CISTOADENOMA APÓCRINO"
    ]
  },
  "labels": {}
}