<?xml version='1.0' encoding='UTF-8'?>
<ANNOTATIONS>
<TEXT>18h: Realização de hemodiálise com duração de 03h e UF de 500ml. 21/03/2012,10:00hs: 8° DI por CA Biliar 5º PO, de Hepatectomia à D + Linfadenectomia + Derivação Biliodigestiva Hepatojejunal, 6º D de TOT + VM, 6º D de acesso venoso central em jugular interna D - curativo trocado em 20/03/12, 5º D de catéter de hemodiálise em subclávia D - curativo trocado em 21/03/12, 6º D de PAM em radial E, 6º D de dreno suctor em flanco D, 6º D de SVD. PA: 108/65, P: 67, FR: 15, T: 35,7ºC, SpO2: 96%, Ramsay 6, pupilas isomióticas, SNG com dieta a 20ml/h, intubada com TOT 7.5, rima 24, em ventilação mecânica modo VCV, Vc 420ml, PEEP 5, FiO2 30%, secreção traqueobrônquica mucosa em média quantidade, acesso venoso central em jugular D com Propofol a 2ml/h + Fentanil 10ml/h, acesso venoso central com catéter de hemodiálise em subclávia D heparinizado, monitorizada, estável hemodinamicamente, MV+ com roncos e bolhosos, PAM em radial E, abdome globoso, flácido, RHA+, FO abdominal limpa e seca, dreno suctor em flanco D com pouca drenagem de secreção hemática, SVD com diurese efetiva, evacuação ausente, extremidades bem perfundidas, higienizada e sentada no leito, pele íntegra. </TEXT>
<TAGS>
<annotation id="1170" tag="Therapeutic or Preventive Procedure" start="19" end="30" text="hemodiálise" abbr="" />
<annotation id="1171" tag="Abbreviation" start="46" end="49" text="03h" abbr="" />
<annotation id="1172" tag="Abbreviation" start="52" end="54" text="UF" abbr="ultrafiltração" />
<annotation id="1173" tag="Quantitative Concept|Abbreviation" start="58" end="63" text="500ml" abbr="" />
<annotation id="1174" tag="Abbreviation" start="88" end="90" text="DI" abbr="" />
<annotation id="1175" tag="Abbreviation|Temporal Concept" start="108" end="110" text="PO" abbr="" />
<annotation id="1176" tag="Therapeutic or Preventive Procedure" start="115" end="127" text="Hepatectomia" abbr="" />
<annotation id="1177" tag="Abbreviation" start="130" end="131" text="D" abbr="Direita" />
<annotation id="1178" tag="Therapeutic or Preventive Procedure" start="134" end="149" text="Linfadenectomia" abbr="" />
<annotation id="1179" tag="Therapeutic or Preventive Procedure|Abbreviation|Medical Device" start="200" end="203" text="TOT" abbr="" />
<annotation id="1180" tag="Abbreviation|Therapeutic or Preventive Procedure" start="206" end="208" text="VM" abbr="" />
<annotation id="1181" tag="Abbreviation" start="213" end="214" text="D" abbr="" />
<annotation id="1182" tag="Medical Device|Therapeutic or Preventive Procedure" start="263" end="271" text="curativo" abbr="" />
<annotation id="1183" tag="Abbreviation" start="296" end="297" text="D" abbr="" />
<annotation id="1184" tag="Medical Device|Therapeutic or Preventive Procedure" start="341" end="349" text="curativo" abbr="" />
<annotation id="1185" tag="Abbreviation" start="374" end="375" text="D" abbr="" />
<annotation id="1186" tag="Abbreviation|Therapeutic or Preventive Procedure" start="379" end="382" text="PAM" abbr="" />
<annotation id="1187" tag="Abbreviation" start="399" end="400" text="D" abbr="" />
<annotation id="1188" tag="Body Location or Region" start="420" end="426" text="flanco" abbr="" />
<annotation id="1189" tag="Spatial Concept|Abbreviation" start="427" end="428" text="D" abbr="Direita" />
<annotation id="1190" tag="Abbreviation" start="433" end="434" text="D" abbr="" />
<annotation id="1191" tag="Medical Device|Therapeutic or Preventive Procedure|Abbreviation" start="438" end="441" text="SVD" abbr="Sonda Vesical de Demora" />
<annotation id="1192" tag="Quantitative Concept" start="447" end="453" text="108/65" abbr="" />
<annotation id="1193" tag="Quantitative Concept" start="458" end="460" text="67" abbr="" />
<annotation id="1194" tag="Quantitative Concept" start="466" end="468" text="15" abbr="" />
<annotation id="1195" tag="Abbreviation" start="481" end="485" text="SpO2" abbr="Saturação Parcial de Oxigênio" />
<annotation id="1196" tag="Quantitative Concept" start="487" end="490" text="96%" abbr="" />
<annotation id="1197" tag="Medical Device|Therapeutic or Preventive Procedure|Abbreviation" start="523" end="526" text="SNG" abbr="Sonda Nasogástrica" />
<annotation id="1198" tag="Food" start="531" end="536" text="dieta" abbr="" />
<annotation id="1199" tag="Quantitative Concept|Abbreviation" start="539" end="545" text="20ml/h" abbr="20 mililitro por hora" />
<annotation id="1200" tag="Medical Device" start="560" end="563" text="TOT" abbr="" />
<annotation id="1201" tag="Quantitative Concept" start="564" end="565" text="7" abbr="" />
<annotation id="1202" tag="Body Part, Organ, or Organ Component" start="569" end="573" text="rima" abbr="" />
<annotation id="1203" tag="Quantitative Concept" start="574" end="576" text="24" abbr="" />
<annotation id="1204" tag="Abbreviation" start="611" end="613" text="Vc" abbr="volume controlada" />
<annotation id="1205" tag="Abbreviation|Quantitative Concept" start="614" end="619" text="420ml" abbr="" />
<annotation id="1206" tag="Abbreviation" start="621" end="625" text="PEEP" abbr="Pressão Expiratória Positiva Final" />
<annotation id="1207" tag="Quantitative Concept" start="626" end="627" text="5" abbr="" />
<annotation id="1208" tag="Abbreviation" start="629" end="633" text="FiO2" abbr="Fração de oxigênio inspirado" />
<annotation id="1209" tag="Quantitative Concept" start="634" end="637" text="30%" abbr="" />
<annotation id="1210" tag="Organic Chemical|Pharmacologic Substance" start="732" end="740" text="Propofol" abbr="" />
<annotation id="1211" tag="Quantitative Concept|Abbreviation" start="743" end="748" text="2ml/h" abbr="2 mililitro por hora" />
<annotation id="1212" tag="Pharmacologic Substance|Organic Chemical" start="751" end="759" text="Fentanil" abbr="" />
<annotation id="1213" tag="Quantitative Concept|Abbreviation" start="760" end="766" text="10ml/h" abbr="10 mililitro por hora" />
<annotation id="1214" tag="Qualitative Concept|Therapeutic or Preventive Procedure" start="832" end="844" text="heparinizado" abbr="" />
<annotation id="1215" tag="Diagnostic Procedure|Finding" start="846" end="858" text="monitorizada" abbr="" />
<annotation id="1216" tag="Finding|Abbreviation" start="887" end="890" text="MV+" abbr="Murmúrios Vesiculares presentes" />
<annotation id="1217" tag="Qualitative Concept" start="904" end="912" text="bolhosos" abbr="" />
<annotation id="1218" tag="Abbreviation" start="914" end="917" text="PAM" abbr="" />
<annotation id="1219" tag="Body Location or Region" start="931" end="937" text="abdome" abbr="" />
<annotation id="1220" tag="Sign or Symptom" start="938" end="945" text="globoso" abbr="" />
<annotation id="1221" tag="Finding" start="947" end="954" text="flácido" abbr="" />
<annotation id="1222" tag="Finding|Abbreviation" start="956" end="960" text="RHA+" abbr="Ruídos hidroaéreos presentes" />
<annotation id="1223" tag="Abbreviation" start="962" end="964" text="FO" abbr="ferida operatória" />
<annotation id="1224" tag="Body Location or Region" start="965" end="974" text="abdominal" abbr="" />
<annotation id="1225" tag="Finding" start="975" end="980" text="limpa" abbr="" />
<annotation id="1226" tag="Finding" start="983" end="987" text="seca" abbr="" />
<annotation id="1227" tag="Body Location or Region" start="1005" end="1011" text="flanco" abbr="" />
<annotation id="1228" tag="Abbreviation" start="1012" end="1013" text="D" abbr="Direita" />
<annotation id="1229" tag="Therapeutic or Preventive Procedure|Abbreviation|Medical Device" start="1055" end="1058" text="SVD" abbr="" />
<annotation id="1230" tag="Finding" start="1129" end="1140" text="higienizada" abbr="" />
<annotation id="1231" tag="Abbreviation|Neoplastic Process" start="95" end="104" text="CA Biliar" />
<annotation id="1232" tag="Therapeutic or Preventive Procedure" start="152" end="190" text="Derivação Biliodigestiva Hepatojejunal" />
<annotation id="1233" tag="Medical Device|Therapeutic or Preventive Procedure" start="218" end="239" text="acesso venoso central" />
<annotation id="1234" tag="Abbreviation|Body Part, Organ, or Organ Component" start="243" end="258" text="jugular interna" />
<annotation id="1235" tag="Medical Device|Therapeutic or Preventive Procedure" start="301" end="323" text="catéter de hemodiálise" />
<annotation id="1236" tag="Abbreviation|Body Part, Organ, or Organ Component" start="327" end="338" text="subclávia D" />
<annotation id="1237" tag="Abbreviation|Body Part, Organ, or Organ Component" start="386" end="394" text="radial E" />
<annotation id="1238" tag="Medical Device|Therapeutic or Preventive Procedure" start="404" end="416" text="dreno suctor" />
<annotation id="1239" tag="Quantitative Concept" start="473" end="479" text="35 , 7ºC" />
<annotation id="1240" tag="Sign or Symptom" start="492" end="500" text="Ramsay 6" />
<annotation id="1241" tag="Sign or Symptom" start="502" end="521" text="pupilas isomióticas" />
<annotation id="1242" tag="Abbreviation|Therapeutic or Preventive Procedure" start="581" end="609" text="ventilação mecânica modo VCV" />
<annotation id="1243" tag="Body Substance|Finding" start="639" end="671" text="secreção traqueobrônquica mucosa" />
<annotation id="1244" tag="Quantitative Concept" start="675" end="691" text="média quantidade" />
<annotation id="1245" tag="Medical Device|Therapeutic or Preventive Procedure" start="693" end="714" text="acesso venoso central" />
<annotation id="1246" tag="Abbreviation|Body Part, Organ, or Organ Component" start="718" end="727" text="jugular D" />
<annotation id="1247" tag="Medical Device|Therapeutic or Preventive Procedure" start="768" end="789" text="acesso venoso central" />
<annotation id="1248" tag="Abbreviation|Body Part, Organ, or Organ Component" start="820" end="831" text="subclávia D" />
<annotation id="1249" tag="Finding" start="860" end="885" text="estável hemodinamicamente" />
<annotation id="1250" tag="Abbreviation|Body Part, Organ, or Organ Component" start="921" end="929" text="radial E" />
<annotation id="1251" tag="Therapeutic or Preventive Procedure|Medical Device" start="989" end="1001" text="dreno suctor" />
<annotation id="1252" tag="Finding|Qualitative Concept" start="1018" end="1032" text="pouca drenagem" />
<annotation id="1253" tag="Sign or Symptom" start="1036" end="1053" text="secreção hemática" />
<annotation id="1254" tag="Finding|Physiologic Function" start="1063" end="1078" text="diurese efetiva" />
<annotation id="1255" tag="Finding|Negation|Physiologic Function" start="1080" end="1097" text="evacuação ausente" />
<annotation id="1256" tag="Finding" start="1099" end="1127" text="extremidades bem perfundidas" />
<annotation id="1257" tag="Finding" start="1143" end="1159" text="sentada no leito" />
<annotation id="1258" tag="Finding" start="1161" end="1173" text="pele íntegra" />
</TAGS>
<RELATIONS>
<rel annotation1="1172" annotation2="1173" reltype="associated_with" />
<rel annotation1="1175" annotation2="1232" reltype="associated_with" />
<rel annotation1="1175" annotation2="1176" reltype="associated_with" />
<rel annotation1="1175" annotation2="1178" reltype="associated_with" />
<rel annotation1="1177" annotation2="1176" reltype="associated_with" />
<rel annotation1="1180" annotation2="1179" reltype="associated_with" />
<rel annotation1="1184" annotation2="1236" reltype="associated_with" />
<rel annotation1="1186" annotation2="1237" reltype="associated_with" />
<rel annotation1="1188" annotation2="1238" reltype="associated_with" />
<rel annotation1="1189" annotation2="1188" reltype="associated_with" />
<rel annotation1="1195" annotation2="1196" reltype="associated_with" />
<rel annotation1="1197" annotation2="1198" reltype="associated_with" />
<rel annotation1="1198" annotation2="1199" reltype="associated_with" />
<rel annotation1="1201" annotation2="1200" reltype="associated_with" />
<rel annotation1="1203" annotation2="1202" reltype="associated_with" />
<rel annotation1="1204" annotation2="1205" reltype="associated_with" />
<rel annotation1="1207" annotation2="1206" reltype="associated_with" />
<rel annotation1="1208" annotation2="1209" reltype="associated_with" />
<rel annotation1="1211" annotation2="1210" reltype="associated_with" />
<rel annotation1="1213" annotation2="1212" reltype="associated_with" />
<rel annotation1="1217" annotation2="1216" reltype="associated_with" />
<rel annotation1="1220" annotation2="1219" reltype="associated_with" />
<rel annotation1="1221" annotation2="1219" reltype="associated_with" />
<rel annotation1="1222" annotation2="1219" reltype="associated_with" />
<rel annotation1="1223" annotation2="1224" reltype="associated_with" />
<rel annotation1="1225" annotation2="1224" reltype="associated_with" />
<rel annotation1="1226" annotation2="1224" reltype="associated_with" />
<rel annotation1="1227" annotation2="1251" reltype="associated_with" />
<rel annotation1="1228" annotation2="1251" reltype="associated_with" />
<rel annotation1="1228" annotation2="1227" reltype="associated_with" />
<rel annotation1="1229" annotation2="1254" reltype="associated_with" />
<rel annotation1="1234" annotation2="1233" reltype="associated_with" />
<rel annotation1="1246" annotation2="1245" reltype="associated_with" />
<rel annotation1="1250" annotation2="1218" reltype="associated_with" />
<rel annotation1="1252" annotation2="1253" reltype="associated_with" />
</RELATIONS>
</ANNOTATIONS>