<?xml version='1.0' encoding='UTF-8'?>
<ANNOTATIONS>
<TEXT>ÀS 03:50 H: CLIENTE REALIZOU RNM DE CRANIO NO CEDIP, SEGUNDO INFORMAÇÕES RECEBIDAS PELA FUNCIONÁRIA MARIA, QUE ACOMPANHOU CLIENTE NA REMOÇÃO, QUADRO DA CLIENTE GRAVE, SENDO COMUNICADO DRº VITAL BRASIL, DA NEURO. FILMES NA UNIDADE, SEM LAUDO. SEGUE LUCIDA, COMUNICATIVA, REPOUSO, EUPNEICA, AFEBRIL. NEGA CEFALEIA, EMESE. SEGUE EM OBSERVAÇÃO E CUIDADOS. Às 11:30h: Dormindo, repouso no leito, febril, sudoreico, traqueostomizado, ar ambiente, aspirado media quantidade de secreção de aspecto purulento, gastrostomia funcionante com dietoterapia, acesso venoso em MSD com SRT em curso, uso de fralda para eliminações, precaução por contato. Às 16:03: 1° di com hx de agressão + fx de orbita esquerda. No momento, consciente, orientado, calmo, eupneico, respirando em ar ambiente, comunicativo, em repouso no leito, acesso venoso em mse com soroterapia em curso, apresenta hematoma + edema em região orbital bilateral, sutura e curativo em região orbital esquerda, refere algia no local, refere algia também em hemitórax esquerdo, aceitando bem a dieta, eliminações ausentes até o momento, segue sob cuidados. </TEXT>
<TAGS>
<annotation id="4875" tag="Patient or Disabled Group" start="12" end="19" text="CLIENTE" abbr="" />
<annotation id="4876" tag="Health Care Related Organization" start="46" end="51" text="CEDIP" abbr="" />
<annotation id="4877" tag="Patient or Disabled Group" start="122" end="129" text="CLIENTE" abbr="" />
<annotation id="4878" tag="Patient or Disabled Group" start="152" end="159" text="CLIENTE" abbr="" />
<annotation id="4879" tag="Abbreviation|Health Care Related Organization" start="205" end="210" text="NEURO" abbr="" />
<annotation id="4880" tag="Health Care Related Organization" start="222" end="229" text="UNIDADE" abbr="" />
<annotation id="4881" tag="Laboratory or Test Result" start="235" end="240" text="LAUDO" abbr="" />
<annotation id="4882" tag="Finding" start="248" end="254" text="LUCIDA" abbr="" />
<annotation id="4883" tag="Finding" start="256" end="268" text="COMUNICATIVA" abbr="" />
<annotation id="4884" tag="Finding|Therapeutic or Preventive Procedure" start="270" end="277" text="REPOUSO" abbr="" />
<annotation id="4885" tag="Finding" start="279" end="287" text="EUPNEICA" abbr="" />
<annotation id="4886" tag="Negation|Finding" start="289" end="296" text="AFEBRIL" abbr="" />
<annotation id="4887" tag="Negation" start="298" end="302" text="NEGA" abbr="" />
<annotation id="4888" tag="Sign or Symptom" start="303" end="311" text="CEFALEIA" abbr="" />
<annotation id="4889" tag="Sign or Symptom" start="313" end="318" text="EMESE" abbr="" />
<annotation id="4890" tag="Health Care Activity" start="329" end="339" text="OBSERVAÇÃO" abbr="" />
<annotation id="4891" tag="Health Care Activity" start="342" end="350" text="CUIDADOS" abbr="" />
<annotation id="4892" tag="Finding" start="363" end="371" text="Dormindo" abbr="" />
<annotation id="4893" tag="Sign or Symptom" start="391" end="397" text="febril" abbr="" />
<annotation id="4894" tag="Sign or Symptom" start="399" end="408" text="sudoreico" abbr="" />
<annotation id="4895" tag="Finding|Therapeutic or Preventive Procedure" start="410" end="426" text="traqueostomizado" abbr="" />
<annotation id="4896" tag="Therapeutic or Preventive Procedure" start="441" end="449" text="aspirado" abbr="" />
<annotation id="4897" tag="Body Substance" start="470" end="478" text="secreção" abbr="" />
<annotation id="4898" tag="Abbreviation|Body Location or Region" start="561" end="564" text="MSD" abbr="" />
<annotation id="4899" tag="Manufactured Object" start="590" end="596" text="fralda" abbr="" />
<annotation id="4900" tag="Abbreviation" start="658" end="660" text="hx" abbr="" />
<annotation id="4901" tag="Injury or Poisoning" start="664" end="672" text="agressão" abbr="" />
<annotation id="4902" tag="Finding" start="710" end="720" text="consciente" abbr="" />
<annotation id="4903" tag="Finding" start="722" end="731" text="orientado" abbr="" />
<annotation id="4904" tag="Finding" start="733" end="738" text="calmo" abbr="" />
<annotation id="4905" tag="Finding" start="740" end="748" text="eupneico" abbr="" />
<annotation id="4906" tag="Finding" start="777" end="789" text="comunicativo" abbr="" />
<annotation id="4907" tag="Body Location or Region|Abbreviation" start="829" end="832" text="mse" abbr="Membro Superior Esquerdo" />
<annotation id="4908" tag="Pathologic Function|Sign or Symptom" start="869" end="877" text="hematoma" abbr="" />
<annotation id="4909" tag="Pathologic Function|Sign or Symptom" start="880" end="885" text="edema" abbr="" />
<annotation id="4910" tag="Therapeutic or Preventive Procedure" start="915" end="921" text="sutura" abbr="" />
<annotation id="4911" tag="Therapeutic or Preventive Procedure|Medical Device" start="924" end="932" text="curativo" abbr="" />
<annotation id="4912" tag="Spatial Concept" start="951" end="959" text="esquerda" abbr="" />
<annotation id="4913" tag="Sign or Symptom" start="968" end="973" text="algia" abbr="" />
<annotation id="4914" tag="Body Location or Region" start="977" end="982" text="local" abbr="" />
<annotation id="4915" tag="Sign or Symptom" start="991" end="996" text="algia" abbr="" />
<annotation id="4916" tag="Body Location or Region" start="1007" end="1016" text="hemitórax" abbr="" />
<annotation id="4917" tag="Spatial Concept" start="1017" end="1025" text="esquerdo" abbr="" />
<annotation id="4918" tag="Physiologic Function" start="1050" end="1061" text="eliminações" abbr="" />
<annotation id="4919" tag="Negation" start="1062" end="1070" text="ausentes" abbr="" />
<annotation id="4920" tag="Health Care Activity" start="1096" end="1104" text="cuidados" abbr="" />
<annotation id="4921" tag="Abbreviation|Diagnostic Procedure" start="29" end="42" text="RNM DE CRANIO" />
<annotation id="4922" tag="Finding|Therapeutic or Preventive Procedure" start="373" end="389" text="repouso no leito" />
<annotation id="4923" tag="Finding" start="428" end="439" text="ar ambiente" />
<annotation id="4924" tag="Qualitative Concept" start="450" end="466" text="media quantidade" />
<annotation id="4925" tag="Sign or Symptom" start="482" end="499" text="aspecto purulento" />
<annotation id="4926" tag="Therapeutic or Preventive Procedure" start="501" end="542" text="gastrostomia funcionante com dietoterapia" />
<annotation id="4927" tag="Medical Device|Therapeutic or Preventive Procedure" start="544" end="557" text="acesso venoso" />
<annotation id="4928" tag="Abbreviation|Therapeutic or Preventive Procedure" start="569" end="581" text="SRT em curso" />
<annotation id="4929" tag="Therapeutic or Preventive Procedure" start="615" end="636" text="precaução por contato" />
<annotation id="4930" tag="Abbreviation|Injury or Poisoning" start="675" end="696" text="fx de orbita esquerda" />
<annotation id="4931" tag="Temporal Concept" start="698" end="708" text="No momento" />
<annotation id="4932" tag="Finding" start="750" end="775" text="respirando em ar ambiente" />
<annotation id="4933" tag="Finding|Therapeutic or Preventive Procedure" start="794" end="810" text="repouso no leito" />
<annotation id="4934" tag="Medical Device|Therapeutic or Preventive Procedure" start="812" end="825" text="acesso venoso" />
<annotation id="4935" tag="Therapeutic or Preventive Procedure" start="837" end="857" text="soroterapia em curso" />
<annotation id="4936" tag="Finding" start="1027" end="1040" text="aceitando bem" />
<annotation id="4937" tag="Temporal Concept" start="1071" end="1084" text="até o momento" />
</TAGS>
<RELATIONS>
<rel annotation1="4887" annotation2="4888" reltype="negation_of" />
</RELATIONS>
</ANNOTATIONS>