<?xml version='1.0' encoding='UTF-8'?>
<ANNOTATIONS>
<TEXT>48 anos, 104 kg, 1m54.
solteira com 4 filhos.
aposentada por invalidez; mãe acima do peso; já faz 14 anos que começou a engordar.</TEXT>
<TAGS>
<annotation id="7190" tag="Quantitative Concept" start="17" end="21" text="1m54" abbr="" />
<annotation id="7191" tag="Finding" start="23" end="31" text="solteira" abbr="" />
<annotation id="7192" tag="Quantitative Concept" start="36" end="37" text="4" abbr="" />
<annotation id="7193" tag="Family Group" start="38" end="44" text="filhos" abbr="" />
<annotation id="7194" tag="Family Group" start="72" end="75" text="mãe" abbr="" />
<annotation id="7195" tag="Quantitative Concept" start="9" end="15" text="104 kg" />
</TAGS>
<RELATIONS>
</RELATIONS>
</ANNOTATIONS>