<?xml version='1.0' encoding='UTF-8'?>
<ANNOTATIONS>
<TEXT>Às 13:30HS: ORIENTADO, CALMO, COMUNICATIVO, EUPNEICO EM AR AMBIENTE, CORADO, MEDICO DA ORTOPEDIA ORIENTOU PARA JEJUM APÓS ALMOÇO, PARA PROCEDIMENTO NO CENTRO CIRURGICO, ACESSO VENOSO PERIFERICO EM ANTEBRAÇO DIREITO SALINIZADO NO MOMENTO, CURATIVO + FIXADOR EXTERNO, EM MEMBRO INFERIOR ESQUERDO, APRESENTA FLICTENAS EM DORSO DO PÉ, RELATA ALGIA; FOI MEDICADO CONFORME PRESCRIÇÃO MÉDICA. SONDA VESICAL DE DEMORA COM DÉBITO CITRINO, segue sob cuidados. # AVC ISQUEMICO. # S: SEM QUEIXAS NO PERIODO. # O: GLASGOW ESTIMADO EM 14, PUPILAS ISOFOTO, AFEBRIL, NORMOCÁRDICA, NORMOTENSA, SNE DIETA EM CURSO 75 ML/H EM BOMBA INFUSORA, ACESSO VENOSO PERIFÉRICO EM MSD SALINIZADO, ABDOMEN PLANO, PALPÁVEL, REGIÃO DORSAL E SACRA ÍNTEGRA, EXTREMIDADES AQUECIDAS E PERFUNDIDAS, REALZIADO MEDIDAS DE HIGIENE E CONFORTO. # A: BEG. # P: SEGUIR PRESCRIÇÃO DE ENFERMAGEM E MULTIDISCIPLINAR. OBS: COMUNICO SERVIÇO SOCIAL PARA SOLICITAR A PRESENÇA DA FAMÍLIA PARA ORIENTAÇÕES DE ALTA, AGUARDO CONTATO.</TEXT>
<TAGS>
<annotation id="8139" tag="Finding" start="12" end="21" text="ORIENTADO" abbr="" />
<annotation id="8140" tag="Finding" start="23" end="28" text="CALMO" abbr="" />
<annotation id="8141" tag="Finding" start="30" end="42" text="COMUNICATIVO" abbr="" />
<annotation id="8142" tag="Finding" start="69" end="75" text="CORADO" abbr="" />
<annotation id="8143" tag="Professional or Occupational Group" start="77" end="83" text="MEDICO" abbr="" />
<annotation id="8144" tag="Health Care Related Organization" start="87" end="96" text="ORTOPEDIA" abbr="" />
<annotation id="8145" tag="Therapeutic or Preventive Procedure" start="111" end="116" text="JEJUM" abbr="" />
<annotation id="8146" tag="Therapeutic or Preventive Procedure" start="135" end="147" text="PROCEDIMENTO" abbr="" />
<annotation id="8147" tag="Therapeutic or Preventive Procedure|Finding" start="215" end="225" text="SALINIZADO" abbr="" />
<annotation id="8148" tag="Medical Device|Therapeutic or Preventive Procedure" start="238" end="246" text="CURATIVO" abbr="" />
<annotation id="8149" tag="Sign or Symptom" start="305" end="314" text="FLICTENAS" abbr="" />
<annotation id="8150" tag="Sign or Symptom" start="338" end="343" text="ALGIA" abbr="" />
<annotation id="8151" tag="Health Care Activity|Therapeutic or Preventive Procedure" start="349" end="357" text="MEDICADO" abbr="" />
<annotation id="8152" tag="Health Care Activity" start="440" end="448" text="cuidados" abbr="" />
<annotation id="8153" tag="Sign or Symptom" start="476" end="483" text="QUEIXAS" abbr="" />
<annotation id="8154" tag="Negation|Finding" start="542" end="549" text="AFEBRIL" abbr="" />
<annotation id="8155" tag="Finding" start="551" end="563" text="NORMOCÁRDICA" abbr="" />
<annotation id="8156" tag="Finding" start="565" end="575" text="NORMOTENSA" abbr="" />
<annotation id="8157" tag="Abbreviation|Medical Device|Therapeutic or Preventive Procedure" start="577" end="580" text="SNE" abbr="" />
<annotation id="8158" tag="Abbreviation|Body Location or Region" start="651" end="654" text="MSD" abbr="" />
<annotation id="8159" tag="Finding|Therapeutic or Preventive Procedure" start="655" end="665" text="SALINIZADO" abbr="" />
<annotation id="8160" tag="Body Location or Region" start="667" end="674" text="ABDOMEN" abbr="" />
<annotation id="8161" tag="Finding" start="675" end="680" text="PLANO" abbr="" />
<annotation id="8162" tag="Finding" start="682" end="690" text="PALPÁVEL" abbr="" />
<annotation id="8163" tag="Body Location or Region" start="692" end="698" text="REGIÃO" abbr="" />
<annotation id="8164" tag="Body Location or Region" start="699" end="705" text="DORSAL" abbr="" />
<annotation id="8165" tag="Body Location or Region" start="708" end="713" text="SACRA" abbr="" />
<annotation id="8166" tag="Finding" start="714" end="721" text="ÍNTEGRA" abbr="" />
<annotation id="8167" tag="Body Location or Region" start="723" end="735" text="EXTREMIDADES" abbr="" />
<annotation id="8168" tag="Finding" start="736" end="745" text="AQUECIDAS" abbr="" />
<annotation id="8169" tag="Finding|Abbreviation" start="807" end="810" text="BEG" abbr="Bom estado geral" />
<annotation id="8170" tag="Family Group" start="927" end="934" text="FAMÍLIA" abbr="" />
<annotation id="8171" tag="Health Care Activity" start="955" end="959" text="ALTA" abbr="" />
<annotation id="8172" tag="Finding" start="44" end="67" text="EUPNEICO EM AR AMBIENTE" />
<annotation id="8173" tag="Health Care Related Organization" start="151" end="167" text="CENTRO CIRURGICO" />
<annotation id="8174" tag="Medical Device|Therapeutic or Preventive Procedure" start="169" end="193" text="ACESSO VENOSO PERIFERICO" />
<annotation id="8175" tag="Body Part, Organ, or Organ Component" start="197" end="214" text="ANTEBRAÇO DIREITO" />
<annotation id="8176" tag="Medical Device|Therapeutic or Preventive Procedure" start="249" end="264" text="FIXADOR EXTERNO" />
<annotation id="8177" tag="Body Location or Region" start="269" end="293" text="MEMBRO INFERIOR ESQUERDO" />
<annotation id="8178" tag="Body Location or Region" start="318" end="329" text="DORSO DO PÉ" />
<annotation id="8179" tag="Health Care Activity|Intellectual Product" start="367" end="384" text="PRESCRIÇÃO MÉDICA" />
<annotation id="8180" tag="Medical Device|Therapeutic or Preventive Procedure" start="386" end="409" text="SONDA VESICAL DE DEMORA" />
<annotation id="8181" tag="Finding" start="414" end="428" text="DÉBITO CITRINO" />
<annotation id="8182" tag="Abbreviation|Disease or Syndrome" start="452" end="465" text="AVC ISQUEMICO" />
<annotation id="8183" tag="Sign or Symptom" start="501" end="523" text="GLASGOW ESTIMADO EM 14" />
<annotation id="8184" tag="Finding" start="525" end="540" text="PUPILAS ISOFOTO" />
<annotation id="8185" tag="Therapeutic or Preventive Procedure" start="581" end="595" text="DIETA EM CURSO" />
<annotation id="8186" tag="Quantitative Concept" start="596" end="603" text="75 ML/H" />
<annotation id="8187" tag="Drug Delivery Device" start="607" end="621" text="BOMBA INFUSORA" />
<annotation id="8188" tag="Medical Device|Therapeutic or Preventive Procedure" start="623" end="647" text="ACESSO VENOSO PERIFÉRICO" />
<annotation id="8189" tag="Finding" start="746" end="759" text="E PERFUNDIDAS" />
<annotation id="8190" tag="Therapeutic or Preventive Procedure" start="771" end="800" text="MEDIDAS DE HIGIENE E CONFORTO" />
<annotation id="8191" tag="Intellectual Product|Health Care Activity" start="824" end="848" text="PRESCRIÇÃO DE ENFERMAGEM" />
<annotation id="8192" tag="Health Care Related Organization|Professional or Occupational Group" start="883" end="897" text="SERVIÇO SOCIAL" />
</TAGS>
<RELATIONS>
<rel annotation1="8143" annotation2="8144" reltype="associated_with" />
<rel annotation1="8146" annotation2="8173" reltype="associated_with" />
<rel annotation1="8147" annotation2="8174" reltype="associated_with" />
<rel annotation1="8148" annotation2="8176" reltype="associated_with" />
<rel annotation1="8149" annotation2="8178" reltype="associated_with" />
<rel annotation1="8157" annotation2="8185" reltype="associated_with" />
<rel annotation1="8158" annotation2="8188" reltype="associated_with" />
<rel annotation1="8159" annotation2="8188" reltype="associated_with" />
<rel annotation1="8161" annotation2="8160" reltype="associated_with" />
<rel annotation1="8175" annotation2="8174" reltype="associated_with" />
<rel annotation1="8177" annotation2="8176" reltype="associated_with" />
<rel annotation1="8181" annotation2="8180" reltype="associated_with" />
<rel annotation1="8186" annotation2="8185" reltype="associated_with" />
<rel annotation1="8186" annotation2="8187" reltype="associated_with" />
<rel annotation1="8187" annotation2="8185" reltype="associated_with" />
</RELATIONS>
</ANNOTATIONS>