<?xml version='1.0' encoding='UTF-8'?>
<ANNOTATIONS>
<TEXT>MARIA, 75 ANOS,

EM ACOMPANHAMENTO DE DIARREIA DIÁRIA.
NEGA SANGRAMENTO.

SOLICITADO A PACIENTE RETORNAR COM EXAMES (COLONOSCOPIA).        </TEXT>
<TAGS>
<annotation id="11939" tag="Negation" start="55" end="59" text="NEGA" abbr="" />
<annotation id="11940" tag="Finding" start="60" end="71" text="SANGRAMENTO" abbr="" />
<annotation id="11941" tag="Patient or Disabled Group" start="87" end="95" text="PACIENTE" abbr="" />
<annotation id="11942" tag="Diagnostic Procedure" start="109" end="115" text="EXAMES" abbr="" />
<annotation id="11943" tag="Diagnostic Procedure" start="117" end="129" text="COLONOSCOPIA" abbr="" />
<annotation id="11944" tag="Sign or Symptom" start="38" end="53" text="DIARREIA DIÁRIA" />
</TAGS>
<RELATIONS>
<rel annotation1="11939" annotation2="11940" reltype="negation_of" />
<rel annotation1="11942" annotation2="11943" reltype="associated_with" />
</RELATIONS>
</ANNOTATIONS>