<?xml version='1.0' encoding='UTF-8'?>
<ANNOTATIONS>
<TEXT>PO RMS PUNHO D JÁ CICATRIZADO.
BOA ADM PUNHO.
ORIENTO GANHO DE ADM DO 2 E 3 DEDOS.
3 DEDO COM LESÃO TUMORAL DORSAL DA IFP.
SOLICITO US.
RETORNO 24/3/16 PARA DISCUSSÃO E MARCAR RETIRADA DO TUMOR DEDO.

R5 LUCAS.</TEXT>
<TAGS>
<annotation id="12099" tag="Abbreviation|Temporal Concept" start="0" end="2" text="PO" abbr="" />
<annotation id="12100" tag="Therapeutic or Preventive Procedure|Abbreviation" start="3" end="6" text="RMS" abbr="" />
<annotation id="12101" tag="Abbreviation|Spatial Concept" start="13" end="14" text="D" abbr="" />
<annotation id="12102" tag="Finding" start="18" end="29" text="CICATRIZADO" abbr="" />
<annotation id="12103" tag="Qualitative Concept" start="31" end="34" text="BOA" abbr="" />
<annotation id="12104" tag="Abbreviation" start="35" end="38" text="ADM" abbr="amplitude de movimento" />
<annotation id="12105" tag="Health Care Activity" start="46" end="53" text="ORIENTO" abbr="" />
<annotation id="12106" tag="Abbreviation|Diagnostic Procedure" start="132" end="134" text="US" abbr="" />
<annotation id="12107" tag="Health Care Activity" start="136" end="143" text="RETORNO" abbr="" />
<annotation id="12108" tag="Neoplastic Process" start="188" end="193" text="TUMOR" abbr="" />
<annotation id="12109" tag="Body Part, Organ, or Organ Component" start="194" end="198" text="DEDO" abbr="" />
<annotation id="12110" tag="Abbreviation" start="201" end="203" text="R5" abbr="" />
<annotation id="12111" tag="Abbreviation|Therapeutic or Preventive Procedure" start="54" end="66" text="GANHO DE ADM" />
<annotation id="12112" tag="Body Part, Organ, or Organ Component" start="70" end="81" text="2 E 3 DEDOS" />
<annotation id="12113" tag="Body Part, Organ, or Organ Component" start="83" end="89" text="3 DEDO" />
<annotation id="12114" tag="Neoplastic Process" start="94" end="107" text="LESÃO TUMORAL" />
</TAGS>
<RELATIONS>
<rel annotation1="12099" annotation2="12100" reltype="associated_with" />
<rel annotation1="12103" annotation2="12104" reltype="associated_with" />
<rel annotation1="12105" annotation2="12111" reltype="associated_with" />
<rel annotation1="12108" annotation2="12109" reltype="associated_with" />
<rel annotation1="12112" annotation2="12111" reltype="associated_with" />
<rel annotation1="12113" annotation2="12114" reltype="associated_with" />
</RELATIONS>
</ANNOTATIONS>