<?xml version='1.0' encoding='UTF-8'?>
<ANNOTATIONS>
<TEXT>PACIENTE COM FX DE TNZ ESQUERDO HÁ 4 MESES.
APRESENTA DEISCENCIA DE SUTURA EM FIBULA.
AO RX: FRATURA CONSOLIDADA.

CD: SOLICITO FST VIA UBS. RETORNO EM 2 MESES.

R2 LUCAS.</TEXT>
<TAGS>
<annotation id="12269" tag="Patient or Disabled Group" start="0" end="8" text="PACIENTE" abbr="" />
<annotation id="12270" tag="Spatial Concept" start="23" end="31" text="ESQUERDO" abbr="" />
<annotation id="12271" tag="Diagnostic Procedure" start="89" end="91" text="RX" abbr="" />
<annotation id="12272" tag="Therapeutic or Preventive Procedure|Abbreviation" start="128" end="131" text="FST" abbr="fisioterapia" />
<annotation id="12273" tag="Abbreviation|Health Care Related Organization" start="136" end="139" text="UBS" abbr="" />
<annotation id="12274" tag="Abbreviation" start="162" end="164" text="R2" abbr="" />
<annotation id="12275" tag="Abbreviation|Injury or Poisoning" start="13" end="22" text="FX DE TNZ" />
<annotation id="12276" tag="Temporal Concept" start="35" end="42" text="4 MESES" />
<annotation id="12277" tag="Sign or Symptom" start="54" end="84" text="DEISCENCIA DE SUTURA EM FIBULA" />
<annotation id="12278" tag="Temporal Concept" start="152" end="159" text="2 MESES" />
</TAGS>
<RELATIONS>
<rel annotation1="12270" annotation2="12275" reltype="associated_with" />
</RELATIONS>
</ANNOTATIONS>