<?xml version='1.0' encoding='UTF-8'?>
<ANNOTATIONS>
<TEXT>Acompanhamento do DM2.  S : Paciente sem queixas referente ao DM. Acompanhamento oftalmológico. Em uso de metformina (3 x 850mg) e glicazida (4 x 30mg), Losartana 50mg 2 x ao dia. Caminhada 50 min 3 vezes por semana.  O : P :69,7 kg, A : 1,54m. IMC : 29,38. CA: ,FC : 68 bpm, FR : 19 mrpm, PA :130/80,  BEG, LOTE, corada, hidratada, acianótica, anicterica, afebril. PC : tórax atípico sem cicatrizes, abaulamentos ou circulação colateral, RCR 2 tempos (B1 e B2), BRNFSS, CPP : livre, expansivo bilateralmente, som claro pulmonar, murmúrios vesiculares presentes, sem ruídos adventíceos. Abdome: globoso, com estrias esbranquiçadas em baixo ventre e cicatriz de colecistectomia e de cesárea. RHA presentes, sem sopros, som timpânico a percussão, sem dor a palpação, presença de hérnia umbilical.  Espaço de Traube livre. Fígado de 9 cm pela hepatimetria. MMII : Sensibilidade presente, sem edema, micose entre terceiro e quarto dedo do pé esquerdo.  A : Exames (03/10/14) :  Glicose : 150, Hb glicada : 8,63%; TG : 255; HDL : 36; LDL : 71; CT : 158; K : 4,8; microalbuminúria de 24 horas: 18; Cl creat calculado  = 98 ml /min;  DM2 não controlado.  P : Adicionar terceiro antidiabético oral.   Encaminhar ao nutricionista.</TEXT>
<TAGS>
<annotation id="21639" tag="Health Care Activity" start="0" end="14" text="Acompanhamento" abbr="" />
<annotation id="21640" tag="Finding|Abbreviation" start="24" end="25" text="S" abbr="" />
<annotation id="21641" tag="Patient or Disabled Group|Patient or Disabled Group" start="28" end="36" text="Paciente" abbr="" />
<annotation id="21642" tag="Negation|Negation" start="37" end="40" text="sem" abbr="" />
<annotation id="21643" tag="Sign or Symptom" start="41" end="48" text="queixas" abbr="" />
<annotation id="21644" tag="Disease or Syndrome|Abbreviation" start="62" end="64" text="DM" abbr="diabetes mellitus" />
<annotation id="21645" tag="Organic Chemical|Pharmacologic Substance" start="106" end="116" text="metformina" abbr="" />
<annotation id="21646" tag="Organic Chemical|Pharmacologic Substance" start="131" end="140" text="glicazida" abbr="" />
<annotation id="21647" tag="Organic Chemical|Pharmacologic Substance" start="153" end="162" text="Losartana" abbr="" />
<annotation id="21648" tag="Abbreviation" start="218" end="219" text="O" abbr="" />
<annotation id="21649" tag="Abbreviation|Clinical Attribute" start="222" end="223" text="P" abbr="" />
<annotation id="21650" tag="Abbreviation|Clinical Attribute" start="234" end="235" text="A" abbr="" />
<annotation id="21651" tag="Clinical Attribute|Abbreviation" start="245" end="248" text="IMC" abbr="índice de massa corporal" />
<annotation id="21652" tag="Clinical Attribute|Abbreviation" start="258" end="260" text="CA" abbr="" />
<annotation id="21653" tag="Abbreviation|Clinical Attribute" start="263" end="265" text="FC" abbr="" />
<annotation id="21654" tag="Abbreviation|Clinical Attribute" start="276" end="278" text="FR" abbr="" />
<annotation id="21655" tag="Organism Function|Abbreviation|Clinical Attribute" start="290" end="292" text="PA" abbr="" />
<annotation id="21656" tag="Quantitative Concept" start="294" end="300" text="130/80" abbr="" />
<annotation id="21657" tag="Finding|Abbreviation" start="303" end="306" text="BEG" abbr="bom estado geral" />
<annotation id="21658" tag="Abbreviation|Finding" start="308" end="312" text="LOTE" abbr="" />
<annotation id="21659" tag="Finding" start="314" end="320" text="corada" abbr="" />
<annotation id="21660" tag="Finding" start="322" end="331" text="hidratada" abbr="" />
<annotation id="21661" tag="Negation|Sign or Symptom" start="333" end="343" text="acianótica" abbr="" />
<annotation id="21662" tag="Negation|Sign or Symptom" start="345" end="355" text="anicterica" abbr="" />
<annotation id="21663" tag="Sign or Symptom|Negation" start="357" end="364" text="afebril" abbr="" />
<annotation id="21664" tag="Negation" start="385" end="388" text="sem" abbr="" />
<annotation id="21665" tag="Sign or Symptom" start="389" end="399" text="cicatrizes" abbr="" />
<annotation id="21666" tag="Sign or Symptom" start="401" end="413" text="abaulamentos" abbr="" />
<annotation id="21667" tag="Abbreviation|Finding" start="463" end="469" text="BRNFSS" abbr="" />
<annotation id="21668" tag="Body Part, Organ, or Organ Component|Abbreviation" start="471" end="474" text="CPP" abbr="campo pleuro pulmonar" />
<annotation id="21669" tag="Finding" start="477" end="482" text="livre" abbr="" />
<annotation id="21670" tag="Negation" start="563" end="566" text="sem" abbr="" />
<annotation id="21671" tag="Body Part, Organ, or Organ Component" start="587" end="593" text="Abdome" abbr="" />
<annotation id="21672" tag="Sign or Symptom" start="595" end="602" text="globoso" abbr="" />
<annotation id="21673" tag="Sign or Symptom" start="649" end="657" text="cicatriz" abbr="" />
<annotation id="21674" tag="Therapeutic or Preventive Procedure" start="661" end="676" text="colecistectomia" abbr="" />
<annotation id="21675" tag="Therapeutic or Preventive Procedure" start="682" end="689" text="cesárea" abbr="" />
<annotation id="21676" tag="Negation" start="706" end="709" text="sem" abbr="" />
<annotation id="21677" tag="Sign or Symptom" start="710" end="716" text="sopros" abbr="" />
<annotation id="21678" tag="Diagnostic Procedure" start="734" end="743" text="percussão" abbr="" />
<annotation id="21679" tag="Negation" start="745" end="748" text="sem" abbr="" />
<annotation id="21680" tag="Diagnostic Procedure" start="755" end="763" text="palpação" abbr="" />
<annotation id="21681" tag="Diagnostic Procedure" start="840" end="852" text="hepatimetria" abbr="" />
<annotation id="21682" tag="Body Location or Region|Abbreviation" start="854" end="858" text="MMII" abbr="membros inferiores" />
<annotation id="21683" tag="Negation" start="885" end="888" text="sem" abbr="" />
<annotation id="21684" tag="Pathologic Function|Sign or Symptom" start="889" end="894" text="edema" abbr="" />
<annotation id="21685" tag="Disease or Syndrome" start="896" end="902" text="micose" abbr="" />
<annotation id="21686" tag="Abbreviation|Diagnostic Procedure" start="949" end="950" text="A" abbr="" />
<annotation id="21687" tag="Laboratory Procedure" start="953" end="959" text="Exames" abbr="" />
<annotation id="21688" tag="Disease or Syndrome" start="1127" end="1130" text="DM2" abbr="" />
<annotation id="21689" tag="Negation" start="1131" end="1134" text="não" abbr="" />
<annotation id="21690" tag="Abbreviation|Intellectual Product" start="1148" end="1149" text="P" abbr="" />
<annotation id="21691" tag="Health Care Activity" start="1193" end="1203" text="Encaminhar" abbr="" />
<annotation id="21692" tag="Health Care Related Organization|Professional or Occupational Group" start="1207" end="1220" text="nutricionista" abbr="" />
<annotation id="21693" tag="Health Care Activity" start="66" end="94" text="Acompanhamento oftalmológico" />
<annotation id="21694" tag="Finding" start="180" end="215" text="Caminhada 50 min 3 vezes por semana" />
<annotation id="21695" tag="Quantitative Concept" start="225" end="232" text="69 , 7 kg" />
<annotation id="21696" tag="Quantitative Concept" start="238" end="243" text="1 , 54m" />
<annotation id="21697" tag="Quantitative Concept" start="251" end="256" text="29 , 38" />
<annotation id="21698" tag="Quantitative Concept" start="268" end="274" text="68 bpm" />
<annotation id="21699" tag="Quantitative Concept" start="281" end="288" text="19 mrpm" />
<annotation id="21700" tag="Sign or Symptom" start="417" end="437" text="circulação colateral" />
<annotation id="21701" tag="Finding" start="484" end="508" text="expansivo bilateralmente" />
<annotation id="21702" tag="Finding" start="510" end="528" text="som claro pulmonar" />
<annotation id="21703" tag="Finding" start="530" end="561" text="murmúrios vesiculares presentes" />
<annotation id="21704" tag="Sign or Symptom" start="567" end="585" text="ruídos adventíceos" />
<annotation id="21705" tag="Sign or Symptom" start="608" end="630" text="estrias esbranquiçadas" />
<annotation id="21706" tag="Abbreviation|Finding" start="691" end="704" text="RHA presentes" />
<annotation id="21707" tag="Finding" start="718" end="731" text="som timpânico" />
<annotation id="21708" tag="Finding" start="796" end="818" text="Espaço de Traube livre" />
<annotation id="21709" tag="Laboratory or Test Result" start="820" end="831" text="Fígado de 9" />
<annotation id="21710" tag="Finding" start="861" end="883" text="Sensibilidade presente" />
<annotation id="21711" tag="Body Part, Organ, or Organ Component" start="909" end="946" text="terceiro e quarto dedo do pé esquerdo" />
<annotation id="21712" tag="Laboratory or Test Result" start="974" end="987" text="Glicose : 150" />
<annotation id="21713" tag="Laboratory or Test Result" start="989" end="1007" text="Hb glicada : 8 , 63%" />
<annotation id="21714" tag="Laboratory or Test Result" start="1009" end="1017" text="TG : 255" />
<annotation id="21715" tag="Laboratory or Test Result" start="1019" end="1027" text="HDL : 36" />
<annotation id="21716" tag="Laboratory or Test Result" start="1029" end="1037" text="LDL : 71" />
<annotation id="21717" tag="Laboratory or Test Result" start="1039" end="1047" text="CT : 158" />
<annotation id="21718" tag="Laboratory or Test Result" start="1049" end="1056" text="K : 4 , 8" />
<annotation id="21719" tag="Laboratory or Test Result" start="1058" end="1090" text="microalbuminúria de 24 horas : 18" />
<annotation id="21720" tag="Laboratory or Test Result" start="1092" end="1124" text="Cl creat calculado = 98 ml /min" />
<annotation id="21721" tag="Pharmacologic Substance" start="1171" end="1189" text="antidiabético oral" />
</TAGS>
<RELATIONS>
<rel annotation1="21642" annotation2="21643" reltype="negation_of" />
<rel annotation1="21644" annotation2="21643" reltype="associated_with" />
<rel annotation1="21664" annotation2="21666" reltype="negation_of" />
<rel annotation1="21664" annotation2="21700" reltype="negation_of" />
<rel annotation1="21664" annotation2="21665" reltype="negation_of" />
<rel annotation1="21670" annotation2="21704" reltype="negation_of" />
<rel annotation1="21671" annotation2="21672" reltype="associated_with" />
<rel annotation1="21673" annotation2="21674" reltype="associated_with" />
<rel annotation1="21673" annotation2="21675" reltype="associated_with" />
<rel annotation1="21676" annotation2="21677" reltype="negation_of" />
<rel annotation1="21683" annotation2="21684" reltype="negation_of" />
<rel annotation1="21685" annotation2="21711" reltype="associated_with" />
<rel annotation1="21709" annotation2="21681" reltype="associated_with" />
</RELATIONS>
</ANNOTATIONS>