<?xml version='1.0' encoding='UTF-8'?>
<ANNOTATIONS>
<TEXT># 13 PO de drenagem de abscesso cervical odontogenico  # 9 PO de redrenagem de abscesso # 5 PO de redrenagem de abscesso # 4 PO de decorticação pulmonar      Glasgow 15 , pupilas iso foto, AP : mv diminuidos em base D , abd flácido , MMII sem edemas , 2 drenos de penrose em região cervical , drenando secreção purulenta . Respiração espontanea , avp em mse com soroterapia em curso , DTF anterior  posterior  sem fuga , SVD com diurese efetiva . Mantem monitorização cardiaca continua seguie sob cuidados intensivas .  Enfermeira Florence Nightingale.  ABSCESSO RETROFARINGEO E PARAFARINGEO</TEXT>
<TAGS>
<annotation id="23290" tag="Abbreviation" start="92" end="94" text="PO" abbr="" />
<annotation id="23291" tag="Body Part, Organ, or Organ Component" start="171" end="178" text="pupilas" abbr="" />
<annotation id="23292" tag="Abbreviation|Finding" start="179" end="182" text="iso" abbr="" />
<annotation id="23293" tag="Abbreviation|Finding" start="183" end="187" text="foto" abbr="" />
<annotation id="23294" tag="Abbreviation|Diagnostic Procedure" start="189" end="191" text="AP" abbr="" />
<annotation id="23295" tag="Abbreviation|Body Location or Region" start="220" end="223" text="abd" abbr="" />
<annotation id="23296" tag="Finding" start="224" end="231" text="flácido" abbr="" />
<annotation id="23297" tag="Body Location or Region|Abbreviation" start="234" end="238" text="MMII" abbr="Membros Inferiores" />
<annotation id="23298" tag="Negation" start="239" end="242" text="sem" abbr="" />
<annotation id="23299" tag="Sign or Symptom" start="243" end="249" text="edemas" abbr="" />
<annotation id="23300" tag="Abbreviation|Medical Device|Therapeutic or Preventive Procedure" start="347" end="350" text="avp" abbr="" />
<annotation id="23301" tag="Body Location or Region|Abbreviation" start="354" end="357" text="mse" abbr="Membro Superior Esquerdo" />
<annotation id="23302" tag="Therapeutic or Preventive Procedure" start="362" end="373" text="soroterapia" abbr="" />
<annotation id="23303" tag="Therapeutic or Preventive Procedure|Abbreviation" start="385" end="388" text="DTF" abbr="" />
<annotation id="23304" tag="Negation" start="410" end="413" text="sem" abbr="" />
<annotation id="23305" tag="Sign or Symptom" start="414" end="418" text="fuga" abbr="" />
<annotation id="23306" tag="Abbreviation|Medical Device|Therapeutic or Preventive Procedure" start="421" end="424" text="SVD" abbr="" />
<annotation id="23307" tag="Health Care Activity" start="447" end="453" text="Mantem" abbr="" />
<annotation id="23308" tag="Professional or Occupational Group" start="520" end="530" text="Enfermeira" abbr="" />
<annotation id="23309" tag="Body Location or Region" start="563" end="576" text="RETROFARINGEO" abbr="" />
<annotation id="23310" tag="Body Location or Region" start="579" end="591" text="PARAFARINGEO" abbr="" />
<annotation id="23311" tag="Abbreviation|Temporal Concept" start="2" end="7" text="13 PO" />
<annotation id="23312" tag="Therapeutic or Preventive Procedure" start="11" end="53" text="drenagem de abscesso cervical odontogenico" />
<annotation id="23313" tag="Abbreviation|Temporal Concept" start="57" end="61" text="9 PO" />
<annotation id="23314" tag="Therapeutic or Preventive Procedure" start="65" end="87" text="redrenagem de abscesso" />
<annotation id="23315" tag="Therapeutic or Preventive Procedure" start="98" end="120" text="redrenagem de abscesso" />
<annotation id="23316" tag="Abbreviation|Temporal Concept" start="123" end="127" text="4 PO" />
<annotation id="23317" tag="Therapeutic or Preventive Procedure" start="131" end="152" text="decorticação pulmonar" />
<annotation id="23318" tag="Finding" start="158" end="168" text="Glasgow 15" />
<annotation id="23319" tag="Abbreviation|Sign or Symptom" start="194" end="207" text="mv diminuidos" />
<annotation id="23320" tag="Abbreviation|Body Location or Region" start="211" end="217" text="base D" />
<annotation id="23321" tag="Medical Device" start="254" end="271" text="drenos de penrose" />
<annotation id="23322" tag="Body Location or Region" start="275" end="290" text="região cervical" />
<annotation id="23323" tag="Body Substance|Sign or Symptom" start="302" end="320" text="secreção purulenta" />
<annotation id="23324" tag="Organism Function|Finding" start="323" end="344" text="Respiração espontanea" />
<annotation id="23325" tag="Finding|Organism Function" start="429" end="444" text="diurese efetiva" />
<annotation id="23326" tag="Diagnostic Procedure" start="454" end="485" text="monitorização cardiaca continua" />
<annotation id="23327" tag="Health Care Activity" start="497" end="516" text="cuidados intensivas" />
</TAGS>
<RELATIONS>
<rel annotation1="23290" annotation2="23315" reltype="associated_with" />
<rel annotation1="23292" annotation2="23291" reltype="associated_with" />
<rel annotation1="23293" annotation2="23291" reltype="associated_with" />
<rel annotation1="23294" annotation2="23319" reltype="associated_with" />
<rel annotation1="23296" annotation2="23295" reltype="associated_with" />
<rel annotation1="23297" annotation2="23299" reltype="associated_with" />
<rel annotation1="23298" annotation2="23299" reltype="negation_of" />
<rel annotation1="23301" annotation2="23300" reltype="associated_with" />
<rel annotation1="23302" annotation2="23300" reltype="associated_with" />
<rel annotation1="23304" annotation2="23305" reltype="negation_of" />
<rel annotation1="23306" annotation2="23325" reltype="associated_with" />
<rel annotation1="23316" annotation2="23317" reltype="associated_with" />
<rel annotation1="23320" annotation2="23319" reltype="associated_with" />
<rel annotation1="23321" annotation2="23322" reltype="associated_with" />
<rel annotation1="23323" annotation2="23321" reltype="associated_with" />
</RELATIONS>
</ANNOTATIONS>