<?xml version='1.0' encoding='UTF-8'?>
<ANNOTATIONS>
<TEXT>PACIENTE DIABÉTICA, HIPERTENSA, COM CARDIOPATIA ISQUEMICA, INTERNA PARA ANGIOPLASTIA COM IMPLANTE DE STENT EM LESÃO SEGMENTAR SEVERA EM CORONÁRIA DAE, REALIZADA COM SUCESSO E SEM INTERCORRÊNCIAS. RECEBE ALTA EM BOM ESTADO GERAL, COM OS SEGUINTES : - TICLOPIDINA 250 MG 1 CP VO 12/12 HORAS POR 30 DIAS. - AAS 100M G2 CP NO ALMOÇO, CONTÍNUO. - DEMAIS MEDICAÇÕES A CRITÉRIO DO SEU MÉDICO.</TEXT>
<TAGS>
<annotation id="24208" tag="Patient or Disabled Group" start="0" end="8" text="PACIENTE" abbr="" />
<annotation id="24209" tag="Disease or Syndrome" start="9" end="18" text="DIABÉTICA" abbr="" />
<annotation id="24210" tag="Disease or Syndrome" start="20" end="30" text="HIPERTENSA" abbr="" />
<annotation id="24211" tag="Health Care Activity" start="59" end="66" text="INTERNA" abbr="" />
<annotation id="24212" tag="Health Care Activity" start="151" end="160" text="REALIZADA" abbr="" />
<annotation id="24213" tag="Negation" start="175" end="178" text="SEM" abbr="" />
<annotation id="24214" tag="Sign or Symptom" start="179" end="194" text="INTERCORRÊNCIAS" abbr="" />
<annotation id="24215" tag="Health Care Activity" start="203" end="207" text="ALTA" abbr="" />
<annotation id="24216" tag="Pharmacologic Substance|Organic Chemical" start="250" end="261" text="TICLOPIDINA" abbr="" />
<annotation id="24217" tag="Abbreviation" start="274" end="276" text="VO" abbr="" />
<annotation id="24218" tag="Pharmacologic Substance|Organic Chemical|Abbreviation" start="304" end="307" text="AAS" abbr="" />
<annotation id="24219" tag="Temporal Concept" start="322" end="328" text="ALMOÇO" abbr="" />
<annotation id="24220" tag="Qualitative Concept" start="330" end="338" text="CONTÍNUO" abbr="" />
<annotation id="24221" tag="Pharmacologic Substance" start="349" end="359" text="MEDICAÇÕES" abbr="" />
<annotation id="24222" tag="Intellectual Product" start="362" end="370" text="CRITÉRIO" abbr="" />
<annotation id="24223" tag="Professional or Occupational Group" start="378" end="384" text="MÉDICO" abbr="" />
<annotation id="24224" tag="Disease or Syndrome" start="36" end="57" text="CARDIOPATIA ISQUEMICA" />
<annotation id="24225" tag="Therapeutic or Preventive Procedure" start="72" end="106" text="ANGIOPLASTIA COM IMPLANTE DE STENT" />
<annotation id="24226" tag="Sign or Symptom" start="110" end="132" text="LESÃO SEGMENTAR SEVERA" />
<annotation id="24227" tag="Abbreviation|Body Part, Organ, or Organ Component" start="136" end="149" text="CORONÁRIA DAE" />
<annotation id="24228" tag="Finding" start="211" end="227" text="BOM ESTADO GERAL" />
<annotation id="24229" tag="Quantitative Concept" start="262" end="268" text="250 MG" />
<annotation id="24230" tag="Abbreviation|Quantitative Concept" start="269" end="273" text="1 CP" />
<annotation id="24231" tag="Temporal Concept" start="277" end="288" text="12/12 HORAS" />
</TAGS>
<RELATIONS>
<rel annotation1="24213" annotation2="24214" reltype="negation_of" />
<rel annotation1="24215" annotation2="24228" reltype="associated_with" />
<rel annotation1="24216" annotation2="24231" reltype="associated_with" />
<rel annotation1="24225" annotation2="24226" reltype="associated_with" />
<rel annotation1="24226" annotation2="24227" reltype="associated_with" />
</RELATIONS>
</ANNOTATIONS>