<?xml version='1.0' encoding='UTF-8'?>
<ANNOTATIONS>
<TEXT>NEFROPATIA DIABETICA EM TTO CONSERVADOR
CANDIDATA A TX RENAL PREEMPTIVO 
LIBERADA PELA URO E ANESTESIO 
CANDIDATA A TX RENAL PREEMPTIVO
ASSINTOMÁTICA, EXCETO PELOS SINAIS E SINTOMAS ASSOCIADOS A NEUROPATIA PERIFERICA ( DIABETICA / UREMIA)
SEM SINTOMAS URINARIOS
AO EXAME PA 150/100   P 108  T 36  DIURESE FRR NORMAL
HIPOCORADA +
CPP LIVRES
PC RITMO REGULAR, TAQUICARDICO
ABD RHA+, PLANO, FLÁCIDO, CIC CX CST
MMII PULSOS PRESENTES E SIMETRICOS</TEXT>
<TAGS>
<annotation id="27061" tag="Patient or Disabled Group" start="41" end="50" text="CANDIDATA" abbr="" />
<annotation id="27062" tag="Abbreviation|Professional or Occupational Group" start="89" end="92" text="URO" abbr="" />
<annotation id="27063" tag="Abbreviation|Professional or Occupational Group" start="95" end="104" text="ANESTESIO" abbr="" />
<annotation id="27064" tag="Patient or Disabled Group" start="107" end="116" text="CANDIDATA" abbr="" />
<annotation id="27065" tag="Negation|Sign or Symptom" start="140" end="153" text="ASSINTOMÁTICA" abbr="" />
<annotation id="27066" tag="Negation" start="155" end="161" text="EXCETO" abbr="" />
<annotation id="27067" tag="Sign or Symptom" start="168" end="174" text="SINAIS" abbr="" />
<annotation id="27068" tag="Sign or Symptom" start="177" end="185" text="SINTOMAS" abbr="" />
<annotation id="27069" tag="Disease or Syndrome" start="223" end="232" text="DIABETICA" abbr="" />
<annotation id="27070" tag="Sign or Symptom" start="235" end="241" text="UREMIA" abbr="" />
<annotation id="27071" tag="Negation" start="244" end="247" text="SEM" abbr="" />
<annotation id="27072" tag="Clinical Attribute" start="271" end="276" text="EXAME" abbr="" />
<annotation id="27073" tag="Abbreviation|Clinical Attribute" start="277" end="279" text="PA" abbr="" />
<annotation id="27074" tag="Quantitative Concept" start="280" end="287" text="150/100" abbr="" />
<annotation id="27075" tag="Abbreviation|Clinical Attribute" start="290" end="291" text="P" abbr="" />
<annotation id="27076" tag="Quantitative Concept" start="292" end="295" text="108" abbr="" />
<annotation id="27077" tag="Clinical Attribute|Abbreviation" start="297" end="298" text="T" abbr="Temperatura" />
<annotation id="27078" tag="Quantitative Concept" start="299" end="301" text="36" abbr="" />
<annotation id="27079" tag="Organism Function" start="303" end="310" text="DIURESE" abbr="" />
<annotation id="27080" tag="Clinical Attribute|Abbreviation" start="311" end="314" text="FRR" abbr="" />
<annotation id="27081" tag="Finding" start="315" end="321" text="NORMAL" abbr="" />
<annotation id="27082" tag="Sign or Symptom" start="323" end="333" text="HIPOCORADA" abbr="" />
<annotation id="27083" tag="Abbreviation|Clinical Attribute" start="349" end="351" text="PC" abbr="" />
<annotation id="27084" tag="Sign or Symptom" start="367" end="379" text="TAQUICARDICO" abbr="" />
<annotation id="27085" tag="Abbreviation|Body Location or Region" start="381" end="384" text="ABD" abbr="" />
<annotation id="27086" tag="Finding|Abbreviation" start="385" end="389" text="RHA+" abbr="Ruídos Hidroaéreos Presentes" />
<annotation id="27087" tag="Finding" start="391" end="396" text="PLANO" abbr="" />
<annotation id="27088" tag="Finding" start="398" end="405" text="FLÁCIDO" abbr="" />
<annotation id="27089" tag="Pathologic Function|Abbreviation" start="407" end="410" text="CIC" abbr="" />
<annotation id="27090" tag="Body Location or Region|Abbreviation" start="419" end="423" text="MMII" abbr="Membros Inferiores" />
<annotation id="27091" tag="Clinical Attribute" start="424" end="430" text="PULSOS" abbr="" />
<annotation id="27092" tag="Disease or Syndrome" start="0" end="20" text="NEFROPATIA DIABETICA" />
<annotation id="27093" tag="Abbreviation|Therapeutic or Preventive Procedure" start="24" end="39" text="TTO CONSERVADOR" />
<annotation id="27094" tag="Abbreviation|Therapeutic or Preventive Procedure" start="53" end="61" text="TX RENAL" />
<annotation id="27095" tag="Abbreviation|Therapeutic or Preventive Procedure" start="119" end="127" text="TX RENAL" />
<annotation id="27096" tag="Disease or Syndrome" start="199" end="220" text="NEUROPATIA PERIFERICA" />
<annotation id="27097" tag="Sign or Symptom" start="248" end="266" text="SINTOMAS URINARIOS" />
<annotation id="27098" tag="Clinical Attribute|Abbreviation|Finding" start="337" end="347" text="CPP LIVRES" />
<annotation id="27099" tag="Finding" start="352" end="365" text="RITMO REGULAR" />
<annotation id="27100" tag="Abbreviation|Therapeutic or Preventive Procedure" start="411" end="417" text="CX CST" />
</TAGS>
<RELATIONS>
<rel annotation1="27064" annotation2="27095" reltype="associated_with" />
<rel annotation1="27067" annotation2="27096" reltype="associated_with" />
<rel annotation1="27068" annotation2="27096" reltype="associated_with" />
<rel annotation1="27071" annotation2="27097" reltype="negation_of" />
<rel annotation1="27072" annotation2="27073" reltype="associated_with" />
<rel annotation1="27072" annotation2="27075" reltype="associated_with" />
<rel annotation1="27072" annotation2="27077" reltype="associated_with" />
<rel annotation1="27072" annotation2="27082" reltype="associated_with" />
<rel annotation1="27072" annotation2="27079" reltype="associated_with" />
<rel annotation1="27072" annotation2="27080" reltype="associated_with" />
<rel annotation1="27072" annotation2="27098" reltype="associated_with" />
<rel annotation1="27072" annotation2="27083" reltype="associated_with" />
<rel annotation1="27073" annotation2="27074" reltype="associated_with" />
<rel annotation1="27075" annotation2="27076" reltype="associated_with" />
<rel annotation1="27077" annotation2="27078" reltype="associated_with" />
<rel annotation1="27080" annotation2="27081" reltype="associated_with" />
<rel annotation1="27083" annotation2="27099" reltype="associated_with" />
<rel annotation1="27085" annotation2="27087" reltype="associated_with" />
<rel annotation1="27085" annotation2="27088" reltype="associated_with" />
<rel annotation1="27090" annotation2="27091" reltype="associated_with" />
<rel annotation1="27092" annotation2="27093" reltype="associated_with" />
<rel annotation1="27094" annotation2="27061" reltype="associated_with" />
</RELATIONS>
</ANNOTATIONS>