<?xml version='1.0' encoding='UTF-8'?>
<ANNOTATIONS>
<TEXT>Paciente G 2  C 1, TS A+, IG de 39 sem 3 dia(s), INTERNA COM PRÓDROMOS DE TP, HISTÓRIA DE CESÁREA PRÉVIA HÁ MENOS DE 2 ANOS. EVOLUI PARA  Cesárea POR RISCO DE RUPTURA UTERINA  em 02/06/2007 AS 05:25 hs. NASCE RN APGAR 8 / 9, MASC, 3605 G.  EXAMES:  VDRL NR, PN OK.  Apresenta boa evolução puereperal, mamas lactantes, lóquios fisiológicos, útero contraído, SV estáveis. Em condições de alta.  ORIENTAÇÕES:  # AMAMENTAÇÃO EXCLUSIVA POR 6 MESES. # TOMAR AS MEDICAÇÕES PRESCRITAS (SULFATO FERROSO 300MG 3X/DIA LONGE DAS REFEIÇÕES, PREFERENCIALMENTE COM SUCO DE LARANJA OU LIMÃO, POR 90 DIAS - PARACETAMOL 500MG 1-2 CP VO DE 6/6 HS SE DOR). # REAVALIAÇÃO COM GINECOLOGISTA EM 30 DIAS. # LAVAR FERIDA OPERATÓRIA 3X/DIA COM ÁGUA E SABÃO NEUTRO. # RETIRAR OS PONTOS EM 10 DIAS. # RETORNAR À EMERGÊNCIA DESTE HOSPITAL SE SANGRAMENTO AUMENTADO, FEBRE,DOR FORTE OU OUTRAS INTERCORRÊNCIAS. </TEXT>
<TAGS>
<annotation id="41431" tag="Quantitative Concept" start="11" end="12" text="2" abbr="" />
<annotation id="41432" tag="Quantitative Concept" start="16" end="17" text="1" abbr="" />
<annotation id="41433" tag="Abbreviation|Clinical Attribute|Clinical Attribute" start="26" end="28" text="IG" abbr="" />
<annotation id="41434" tag="Health Care Activity|Health Care Activity" start="49" end="56" text="INTERNA" abbr="" />
<annotation id="41435" tag="Organism Function" start="74" end="76" text="TP" abbr="" />
<annotation id="41436" tag="Therapeutic or Preventive Procedure" start="90" end="97" text="CESÁREA" abbr="" />
<annotation id="41437" tag="Temporal Concept" start="98" end="104" text="PRÉVIA" abbr="" />
<annotation id="41438" tag="Temporal Concept|Temporal Concept" start="125" end="131" text="EVOLUI" abbr="" />
<annotation id="41439" tag="Therapeutic or Preventive Procedure|Therapeutic or Preventive Procedure" start="138" end="145" text="Cesárea" abbr="" />
<annotation id="41440" tag="Abbreviation|Age Group" start="209" end="211" text="RN" abbr="" />
<annotation id="41441" tag="Finding" start="225" end="229" text="MASC" abbr="" />
<annotation id="41442" tag="Laboratory or Test Result|Diagnostic Procedure" start="240" end="246" text="EXAMES" abbr="" />
<annotation id="41443" tag="Health Care Activity|Health Care Activity" start="386" end="390" text="alta" abbr="" />
<annotation id="41444" tag="Health Care Activity|Health Care Activity" start="393" end="404" text="ORIENTAÇÕES" abbr="" />
<annotation id="41445" tag="Organism Function" start="409" end="420" text="AMAMENTAÇÃO" abbr="" />
<annotation id="41446" tag="Organic Chemical|Pharmacologic Substance" start="590" end="601" text="PARACETAMOL" abbr="" />
<annotation id="41447" tag="Abbreviation" start="615" end="617" text="VO" abbr="" />
<annotation id="41448" tag="Sign or Symptom|Sign or Symptom" start="631" end="634" text="DOR" abbr="" />
<annotation id="41449" tag="Health Care Activity|Health Care Activity" start="639" end="650" text="REAVALIAÇÃO" abbr="" />
<annotation id="41450" tag="Professional or Occupational Group" start="655" end="668" text="GINECOLOGISTA" abbr="" />
<annotation id="41451" tag="Health Care Activity" start="683" end="688" text="LAVAR" abbr="" />
<annotation id="41452" tag="Quantitative Concept" start="707" end="713" text="3X/DIA" abbr="" />
<annotation id="41453" tag="Inorganic Chemical" start="718" end="722" text="ÁGUA" abbr="" />
<annotation id="41454" tag="Health Care Activity" start="741" end="748" text="RETIRAR" abbr="" />
<annotation id="41455" tag="Manufactured Object" start="752" end="758" text="PONTOS" abbr="" />
<annotation id="41456" tag="Health Care Activity" start="773" end="781" text="RETORNAR" abbr="" />
<annotation id="41457" tag="Health Care Related Organization" start="784" end="794" text="EMERGÊNCIA" abbr="" />
<annotation id="41458" tag="Health Care Related Organization|Manufactured Object|Health Care Related Organization" start="801" end="809" text="HOSPITAL" abbr="" />
<annotation id="41459" tag="Sign or Symptom|Sign or Symptom" start="836" end="841" text="FEBRE" abbr="" />
<annotation id="41460" tag="Sign or Symptom" start="862" end="877" text="INTERCORRÊNCIAS" abbr="" />
<annotation id="41461" tag="Abbreviation|Laboratory or Test Result" start="19" end="24" text="TS A+" />
<annotation id="41462" tag="Abbreviation|Temporal Concept" start="32" end="44" text="39 sem 3 dia" />
<annotation id="41463" tag="Pathologic Function" start="159" end="174" text="RUPTURA UTERINA" />
<annotation id="41464" tag="Laboratory or Test Result" start="212" end="223" text="APGAR 8 / 9" />
<annotation id="41465" tag="Abbreviation|Finding|Quantitative Concept" start="231" end="237" text="3605 G" />
<annotation id="41466" tag="Abbreviation|Laboratory or Test Result" start="249" end="256" text="VDRL NR" />
<annotation id="41467" tag="Abbreviation|Laboratory or Test Result" start="258" end="263" text="PN OK" />
<annotation id="41468" tag="Finding" start="276" end="299" text="boa evolução puereperal" />
<annotation id="41469" tag="Finding" start="301" end="316" text="mamas lactantes" />
<annotation id="41470" tag="Finding" start="318" end="338" text="lóquios fisiológicos" />
<annotation id="41471" tag="Finding" start="340" end="355" text="útero contraído" />
<annotation id="41472" tag="Abbreviation|Finding" start="357" end="368" text="SV estáveis" />
<annotation id="41473" tag="Temporal Concept" start="435" end="442" text="6 MESES" />
<annotation id="41474" tag="Health Care Activity" start="446" end="476" text="TOMAR AS MEDICAÇÕES PRESCRITAS" />
<annotation id="41475" tag="Inorganic Chemical|Pharmacologic Substance" start="478" end="493" text="SULFATO FERROSO" />
<annotation id="41476" tag="Quantitative Concept" start="494" end="506" text="300MG 3X/DIA" />
<annotation id="41477" tag="Temporal Concept" start="507" end="526" text="LONGE DAS REFEIÇÕES" />
<annotation id="41478" tag="Food" start="550" end="574" text="SUCO DE LARANJA OU LIMÃO" />
<annotation id="41479" tag="Temporal Concept" start="580" end="587" text="90 DIAS" />
<annotation id="41480" tag="Quantitative Concept" start="602" end="614" text="500MG 1-2 CP" />
<annotation id="41481" tag="Quantitative Concept" start="621" end="627" text="6/6 HS" />
<annotation id="41482" tag="Temporal Concept" start="669" end="679" text="EM 30 DIAS" />
<annotation id="41483" tag="Injury or Poisoning" start="689" end="706" text="FERIDA OPERATÓRIA" />
<annotation id="41484" tag="Manufactured Object" start="725" end="737" text="SABÃO NEUTRO" />
<annotation id="41485" tag="Temporal Concept" start="762" end="769" text="10 DIAS" />
<annotation id="41486" tag="Sign or Symptom" start="813" end="834" text="SANGRAMENTO AUMENTADO" />
<annotation id="41487" tag="Sign or Symptom" start="842" end="851" text="DOR FORTE" />
</TAGS>
<RELATIONS>
<rel annotation1="41451" annotation2="41483" reltype="associated_with" />
<rel annotation1="41454" annotation2="41455" reltype="associated_with" />
<rel annotation1="41456" annotation2="41457" reltype="associated_with" />
<rel annotation1="41475" annotation2="41476" reltype="associated_with" />
</RELATIONS>
</ANNOTATIONS>