{
  "prontuario_id": 821,
  "text": "Às 14:18 HS: CONSCIENTE, ORIENTADA, EUPNEICA, ACEITA DIETA, CATETER EM JUGULAR ESQ PARA HEMODIÁLISE, ABDOME PLANO, FLÁCIDO, INDOLOR A PALPAÇÃO, DIURESE POUCO VOLUME, EVACUAÇÃO NORMAL, SEM QUEIXAS ALGICAS, SEM FORÇA MUSCULAR EM MMII, MANTEM PRECAUÇÃO DE CONTATO. Às 15:13: CLIENTE REFERE DOR MODERADA EM JOELHO D, CONSCIENTE, COMUNICATIVA, EUPNEICA, REPOUSO NO LEITO, ACEITANDO BEM A DIETA, ACESSO PERIFÉRICO EM MSE SALINIZADO, ABDOMEN GLOBOSO E FLÁCIDO, MANTENDO CATETER PERIDURAL PARA ANALGESIA, CTVO LIMPO E SECO EM MID, PERFUSÃO DISTAL PRESERVADA, MICÇÃO PRESENTE. Às 16:32: FOI DIMINUIDO O GOTEJAMENTO DA NPT EM BI PARA 40 ML/H, CONFORME ORIENTAÇÃO DO DRº VITAL BRASIL. Às 18:16hs: Estavel hemodinamicamente, segue de alta para ala b-16-2 acompanhado dos familiares e a enfermagem. Às 00:18h: encontra-se consciente, orientada, pouco comunicativa, ssvv dentro dos parametros de normalidade, mantendo acesso venoso periférico em MSD permeavel, salinizado no momento, mantem colar cervical, apresenta escoriações em face, sem queixas álgicas, SEGUE CUIDADOS.  ",
  "entities": {
    "Achado": [
      "CONSCIENTE",
      "ORIENTADA",
      "EUPNEICA",
      "FLÁCIDO",
      "COMUNICATIVA",
      "SALINIZADO",
      "LIMPO",
      "SECO",
      "consciente",
      "orientada",
      "permeavel",
      "salinizado",
      "ACEITA DIETA",
      "POUCO VOLUME",
      "EVACUAÇÃO NORMAL",
      "REPOUSO NO LEITO",
      "ACEITANDO BEM",
      "PERFUSÃO DISTAL PRESERVADA",
      "MICÇÃO PRESENTE",
      "Estavel hemodinamicamente",
      "pouco comunicativa",
      "ssvv dentro dos parametros de normalidade"
    ],
    "Dispositivo Médico": [
      "CATETER",
      "CTVO",
      "ACESSO PERIFÉRICO",
      "CATETER PERIDURAL",
      "acesso venoso periférico",
      "colar cervical"
    ],
    "Procedimento Terapêutico ou Preventivo": [
      "CATETER",
      "HEMODIÁLISE",
      "SALINIZADO",
      "CTVO",
      "salinizado",
      "PRECAUÇÃO DE CONTATO",
      "REPOUSO NO LEITO",
      "ACESSO PERIFÉRICO",
      "DIMINUIDO O GOTEJAMENTO DA NPT",
      "acesso venoso periférico",
      "colar cervical"
    ],
    "Localização ou Região Corporal": [
      "ABDOME",
      "MSE",
      "ABDOMEN",
      "MSD",
      "face"
    ],
    "Negação": [
      "INDOLOR",
      "SEM",
      "sem"
    ],
    "Procedimento Diagnóstico": [
      "PALPAÇÃO"
    ],
    "Função Fisiológica": [
      "DIURESE",
      "EVACUAÇÃO NORMAL",
      "MICÇÃO PRESENTE"
    ],
    "Paciente ou Grupo com Deficiência": [
      "CLIENTE"
    ],
    "Abreviação": [
      "MSE",
      "CTVO",
      "BI",
      "DRº",
      "MSD",
      "JUGULAR ESQ",
      "JOELHO D",
      "EM MID",
      "DIMINUIDO O GOTEJAMENTO DA NPT",
      "ssvv dentro dos parametros de normalidade"
    ],
    "Atividade de Assistência à Saúde": [
      "alta",
      "CUIDADOS"
    ],
    "Grupo Familiar": [
      "familiares"
    ],
    "Grupo Profissional ou Ocupacional": [
      "enfermagem"
    ],
    "Lesão ou Envenenamento": [
      "escoriações"
    ],
    "Parte do Corpo, Órgão ou Componente Orgânico": [
      "JUGULAR ESQ",
      "JOELHO D"
    ],
    "Sinal ou Sintoma": [
      "QUEIXAS ALGICAS",
      "DOR MODERADA",
      "queixas álgicas"
    ],
    "Função de Órgão ou Tecido": [
      "FORÇA MUSCULAR"
    ],
    "Conceito Quantitativo": [
      "40 ML/H"
    ]
  },
  "labels": {
    "diminuido o gotejamento da npt": {
      "capitulo": "12.11"
    },
    "queixas algicas": {
      "capitulo": "14.0"
    },
    "jugular esq": {
      "capitulo": "11.51"
    },
    "limpo": {
      "capitulo": "21.11"
    },
    "aceitando bem": {
      "capitulo": "24.11"
    },
    "permeavel": {
      "capitulo": "24.11"
    },
    "abdome": {
      "capitulo": "13.1"
    },
    "perfusão distal preservada": {
      "capitulo": "11.51"
    },
    "queixas álgicas": {
      "capitulo": "14.0"
    },
    "força muscular": {
      "capitulo": "15.1"
    },
    "40 ml/h": {
      "capitulo": "24.11"
    },
    "acesso periférico": {
      "capitulo": "11.51"
    },
    "micção presente": {
      "capitulo": "16.1"
    },
    "familiares": {
      "capitulo": "24.11"
    },
    "alta": {
      "capitulo": "24.11"
    },
    "ctvo": {
      "capitulo": "11.51"
    },
    "salinizado": {
      "capitulo": "24.11"
    },
    "palpação": {
      "capitulo": "15.1"
    },
    "em mid": {
      "capitulo": "11.51"
    },
    "cateter peridural": {
      "capitulo": "11.51"
    },
    "cateter": {
      "capitulo": "11.51"
    },
    "comunicativa": {
      "capitulo": "24.11"
    },
    "mse": {
      "capitulo": "11.51"
    },
    "estavel hemodinamicamente": {
      "capitulo": "24.11"
    },
    "dor moderada": {
      "capitulo": "14.0"
    },
    "diurese": {
      "capitulo": "13.1"
    },
    "face": {
      "capitulo": "14.0"
    },
    "colar cervical": {
      "capitulo": "14.0"
    },
    "precaução de contato": {
      "capitulo": "24.11"
    },
    "hemodiálise": {
      "capitulo": "12.11"
    },
    "repouso no leito": {
      "capitulo": "24.11"
    },
    "pouco volume": {
      "capitulo": "13.1"
    },
    "seco": {
      "capitulo": "14.0"
    },
    "abdomen": {
      "capitulo": "13.1"
    },
    "cliente": {
      "capitulo": "24.11"
    },
    "flácido": {
      "capitulo": "15.1"
    },
    "bi": {
      "capitulo": "11.51"
    },
    "evacuação normal": {
      "capitulo": "13.1"
    },
    "msd": {
      "capitulo": "11.51"
    },
    "joelho d": {
      "capitulo": "15.1"
    },
    "cuidados": {
      "capitulo": "24.11"
    },
    "escoriações": {
      "capitulo": "14.0"
    },
    "consciente": {
      "capitulo": "24.11"
    },
    "ssvv dentro dos parametros de normalidade": {
      "capitulo": "24.11"
    },
    "indolor": {
      "capitulo": "14.0"
    },
    "drº": {
      "capitulo": "24.11"
    },
    "enfermagem": {
      "capitulo": "24.11"
    },
    "aceita dieta": {
      "capitulo": "24.11"
    },
    "acesso venoso periférico": {
      "capitulo": "11.51"
    },
    "sem": {
      "capitulo": "24.11"
    },
    "orientada": {
      "capitulo": "24.11"
    },
    "eupneica": {
      "capitulo": "12.11"
    },
    "pouco comunicativa": {
      "capitulo": "24.11"
    }
  }
}